MANIFEST.in
pip_desc.txt
setup.py
ExtendedOpenGraph/ExtendedOpenGraph.py
ExtendedOpenGraph/__init__.py
ExtendedOpenGraph/test.py
ExtendedOpenGraph.egg-info/PKG-INFO
ExtendedOpenGraph.egg-info/SOURCES.txt
ExtendedOpenGraph.egg-info/dependency_links.txt
ExtendedOpenGraph.egg-info/entry_points.txt
ExtendedOpenGraph.egg-info/not-zip-safe
ExtendedOpenGraph.egg-info/requires.txt
ExtendedOpenGraph.egg-info/top_level.txt