Metadata-Version: 1.1
Name: ExtendedOpenGraph
Version: 0.3
Summary: A module of parsing the open graph protocol and extracing the summary of the web page.
Home-page: https://github.com/AhnSeongHyun/ExtendedOpenGraphParser
Author: SeongHyun.Ahn
Author-email: sh84.ahn@gmail.com
License: MIT
Keywords: opengraph protocol facebook
Platform: UNKNOWN
Classifier: Development Status :: 3 - Alpha
Classifier: Intended Audience :: Developers
Classifier: Programming Language :: Python :: 2.7
Classifier: Topic :: Text Processing :: Markup :: HTML
Classifier: Topic :: Software Development :: Libraries :: Python Modules
